odoo/addons/operating_unit_access_all/README.rst
odoo/addons/operating_unit_access_all/__init__.py
odoo/addons/operating_unit_access_all/__manifest__.py
odoo/addons/operating_unit_access_all/i18n/it.po
odoo/addons/operating_unit_access_all/i18n/operating_unit_access_all.pot
odoo/addons/operating_unit_access_all/readme/CONFIGURE.md
odoo/addons/operating_unit_access_all/readme/CONTRIBUTORS.md
odoo/addons/operating_unit_access_all/readme/DESCRIPTION.md
odoo/addons/operating_unit_access_all/security/operating_unit_security.xml
odoo/addons/operating_unit_access_all/static/description/icon.png
odoo/addons/operating_unit_access_all/static/description/index.html
odoo_addon_operating_unit_access_all-18.0.1.0.0.2.dist-info/METADATA
odoo_addon_operating_unit_access_all-18.0.1.0.0.2.dist-info/WHEEL
odoo_addon_operating_unit_access_all-18.0.1.0.0.2.dist-info/top_level.txt
odoo_addon_operating_unit_access_all-18.0.1.0.0.2.dist-info/RECORD
