Metadata-Version: 2.1
Name: odoo-addon-operating_unit_access_all
Version: 18.0.1.0.0.2
Requires-Python: >=3.10
Requires-Dist: odoo-addon-operating_unit==18.0.*
Requires-Dist: odoo==18.0.*
Summary: Access all Operating Units
Home-page: https://github.com/OCA/operating-unit
License: AGPL-3
Author: Ecosoft,Odoo Community Association (OCA)
Author-email: support@odoo-community.org
Classifier: Programming Language :: Python
Classifier: Framework :: Odoo
Classifier: Framework :: Odoo :: 18.0
Classifier: License :: OSI Approved :: GNU Affero General Public License v3
